pytest_flake8.py
pytest_flake8_v2-1.2.3.dist-info/LICENSE
pytest_flake8_v2-1.2.3.dist-info/METADATA
pytest_flake8_v2-1.2.3.dist-info/WHEEL
pytest_flake8_v2-1.2.3.dist-info/entry_points.txt
pytest_flake8_v2-1.2.3.dist-info/top_level.txt
pytest_flake8_v2-1.2.3.dist-info/RECORD
