Metadata-Version: 2.1
Name: pytest-flake8-v2
Version: 1.2.3
Summary: pytest plugin to check FLAKE8 requirements
Home-page: https://github.com/VRGhost/pytest-flake8
Author: Thorsten Lockert
Author-email: tholo@sigmasoft.com
Maintainer: Ilja Orlovs
Maintainer-email: vrghost@gmail.com
License: BSD License
Platform: UNKNOWN
Classifier: Development Status :: 5 - Production/Stable
Classifier: Intended Audience :: Developers
Classifier: License :: OSI Approved :: BSD License
Classifier: Programming Language :: Python
Classifier: Programming Language :: Python :: Implementation :: CPython
Classifier: Programming Language :: Python :: Implementation :: PyPy
Classifier: Topic :: Software Development
Classifier: Topic :: Software Development :: Quality Assurance
Classifier: Topic :: Software Development :: Testing
Classifier: Operating System :: OS Independent
Requires-Python: >=3.6
License-File: LICENSE
Requires-Dist: flake8 (>=4.0)
Requires-Dist: pytest (>=7.0)
